{
  "project": {
    "pid": "__VIA_PROJECT_ID__",
    "rev": "__VIA_PROJECT_REV_ID__",
    "rev_timestamp": "__VIA_PROJECT_REV_TIMESTAMP__",
    "pname": "DFU - Diabetic Foot Ulcer Detection",
    "creator": "VGG Image Annotator (http://www.robots.ox.ac.uk/~vgg/software/via)",
    "created": 1774460313028,
    "vid_list": [
      "1"
    ]
  },
  "config": {
    "file": {
      "loc_prefix": {
        "1": "",
        "2": "",
        "3": "",
        "4": ""
      }
    },
    "ui": {
      "file_content_align": "center",
      "file_metadata_editor_visible": true,
      "spatial_metadata_editor_visible": true,
      "temporal_segment_metadata_editor_visible": true,
      "gtimeline_visible_row_count": "4"
    }
  },
  "attribute": {
    "1": {
      "aname": "region_type",
      "anchor_id": "1",
      "type": 1,
      "id": 1,
      "options": {
        "1": "pressure_ulcer",
        "2": "at_risk_area",
        "3": "normal_tissue"
      },
      "default_options": []
    }
  },
  "file": {
    "1": {
      "fid": "1",
      "fname": "P041_L.png",
      "type": 2,
      "loc": 1,
      "src": ""
    }
  },
  "metadata": {
    "1_de105ab5": {
      "vid": "1",
      "flg": 0,
      "z": [],
      "xy": [
        2,
        161.30123122556176,
        175.15814619810448,
        28.30179941592242,
        37.52621986129807
      ],
      "av": {
        "1": "2"
      }
    },
    "1_4a872e5d": {
      "vid": "1",
      "flg": 0,
      "z": [],
      "xy": [
        2,
        160.1767927385792,
        133.75734495373348,
        48.93572902632443,
        43.19480465060661
      ],
      "av": {
        "1": "2"
      }
    },
    "1_efd5c69f": {
      "vid": "1",
      "flg": 0,
      "z": [],
      "xy": [
        2,
        139.18630806646158,
        54.34328853087022,
        42.39717082119248,
        30.202605982695562
      ],
      "av": {
        "1": "1"
      }
    }
  },
  "view": {
    "1": {
      "fid_list": [
        "1"
      ]
    }
  }
}