{
  "project": {
    "pid": "__VIA_PROJECT_ID__",
    "rev": "__VIA_PROJECT_REV_ID__",
    "rev_timestamp": "__VIA_PROJECT_REV_TIMESTAMP__",
    "pname": "DFU - Diabetic Foot Ulcer Detection",
    "creator": "VGG Image Annotator (http://www.robots.ox.ac.uk/~vgg/software/via)",
    "created": 1774460313028,
    "vid_list": [
      "1"
    ]
  },
  "config": {
    "file": {
      "loc_prefix": {
        "1": "",
        "2": "",
        "3": "",
        "4": ""
      }
    },
    "ui": {
      "file_content_align": "center",
      "file_metadata_editor_visible": true,
      "spatial_metadata_editor_visible": true,
      "temporal_segment_metadata_editor_visible": true,
      "gtimeline_visible_row_count": "4"
    }
  },
  "attribute": {
    "1": {
      "aname": "region_type",
      "anchor_id": "1",
      "type": 1,
      "id": 1,
      "options": {
        "1": "pressure_ulcer",
        "2": "at_risk_area",
        "3": "normal_tissue"
      },
      "default_options": []
    }
  },
  "file": {
    "1": {
      "fid": "1",
      "fname": "P272_R.png",
      "type": 2,
      "loc": 1,
      "src": ""
    }
  },
  "metadata": {
    "1_8f31a63c": {
      "vid": "1",
      "flg": 0,
      "z": [],
      "xy": [
        2,
        46.878011779055825,
        151.6536873558352,
        29.59585144070306,
        41.22634252020073
      ],
      "av": {
        "1": "1"
      }
    },
    "1_7a962f0d": {
      "vid": "1",
      "flg": 0,
      "z": [],
      "xy": [
        2,
        123.78844578777131,
        116.05851711210397,
        43.41083673333171,
        33.2806416005093
      ],
      "av": {
        "1": "2"
      }
    },
    "1_1a6f7ed6": {
      "vid": "1",
      "flg": 0,
      "z": [],
      "xy": [
        2,
        44.11697331394426,
        91.03239715010346,
        31.285113679184622,
        34.11435975631773
      ],
      "av": {
        "1": "2"
      }
    }
  },
  "view": {
    "1": {
      "fid_list": [
        "1"
      ]
    }
  }
}